[{"year":2009,"time":1251756000000,"data":[{"raw":"10/9 Kollationering i K1","beskrivning":"Kollationering i K1","tag":"meeting","datum":"10/9","time":{"start":1252533600000,"end":1252620000000},"day":{"start":9,"end":9}},{"raw":"18/9-20/9 Internat","beskrivning":"Internat","tag":"tour","datum":"18/9-20/9","time":{"start":1253224800000,"end":1253484000000},"day":{"start":17,"end":19}},{"raw":"17/10 Happening i Ljusgården Teknikringen 78","beskrivning":"Happening i Ljusgården Teknikringen 78","tag":"rehearsal","datum":"17/10","time":{"start":1255737600000,"end":1255824000000},"day":{"start":46.083333333333336,"end":46.083333333333336}},{"raw":"14/11 Smygis på Årsta Teater och 100-klubbens afton","beskrivning":"Smygis på Årsta Teater och 100-klubbens afton","tag":"rehearsal","datum":"14/11","time":{"start":1258156800000,"end":1258243200000},"day":{"start":74.08333333333333,"end":74.08333333333333}},{"raw":"2/12 Premiär på Vasateatern","beskrivning":"Premiär på Vasateatern","tag":"show","datum":"2/12","time":{"start":1259708400000,"end":1259794800000},"day":{"start":92.04166666666667,"end":92.04166666666667}},{"raw":"3/12 Premiär på Vasateatern","beskrivning":"Premiär på Vasateatern","tag":"show","datum":"3/12","time":{"start":1259794800000,"end":1259881200000},"day":{"start":93.04166666666667,"end":93.04166666666667}},{"raw":"4/12 Premiär på Vasateatern","beskrivning":"Premiär på Vasateatern","tag":"show","datum":"4/12","time":{"start":1259881200000,"end":1259967600000},"day":{"start":94.04166666666667,"end":94.04166666666667}},{"raw":"8/12 Stormöte, kl 18 i K1, TR 56","beskrivning":"Stormöte, kl 18 i K1, TR 56","tag":"meeting","datum":"8/12","time":{"start":1260226800000,"end":1260313200000},"day":{"start":98.04166666666667,"end":98.04166666666667}},{"raw":"12/12 Slaskfest","beskrivning":"Slaskfest","tag":"party","datum":"12/12","time":{"start":1260576000000,"end":1260662400000},"day":{"start":102.08333333333333,"end":102.08333333333333}},{"raw":"11/2-15/2 Finland","beskrivning":"Finland","tag":"tour","datum":"11/2-15/2","time":{"start":1265842800000,"end":1266274800000},"day":{"start":163.04166666666666,"end":167.04166666666666}},{"raw":"13/12 Föreställning Finland","beskrivning":"Föreställning Finland","tag":"show","datum":"13/12","time":{"start":1292198400000,"end":1292284800000},"day":{"start":468.0833333333333,"end":468.0833333333333}},{"raw":"1/3 Omgång 2 på Södra teatern","beskrivning":"Omgång 2 på Södra teatern","tag":"show","datum":"1/3","time":{"start":1267398000000,"end":1267484400000},"day":{"start":181.04166666666666,"end":181.04166666666666}},{"raw":"2/3 Bjupp","beskrivning":"Bjupp","tag":"show","datum":"2/3","time":{"start":1267484400000,"end":1267570800000},"day":{"start":182.04166666666666,"end":182.04166666666666}},{"raw":"3/3 KTHs anställda","beskrivning":"KTHs anställda","tag":"show","datum":"3/3","time":{"start":1267570800000,"end":1267657200000},"day":{"start":183.04166666666666,"end":183.04166666666666}},{"raw":"6/3 Slaskfest omg 2","beskrivning":"Slaskfest omg 2","tag":"party","datum":"6/3","time":{"start":1267830000000,"end":1267916400000},"day":{"start":186.04166666666666,"end":186.04166666666666}},{"raw":"23/3 Stormöte kl 18 i L1","beskrivning":"Stormöte kl 18 i L1","tag":"meeting","datum":"23/3","time":{"start":1269298800000,"end":1269385200000},"day":{"start":203.04166666666666,"end":203.04166666666666}},{"raw":"7/4 Köpt föreställning på Södra teatern","beskrivning":"Köpt föreställning på Södra teatern","tag":"show","datum":"7/4","time":{"start":1270591200000,"end":1270677600000},"day":{"start":218,"end":218}},{"raw":"10/4 Kårspexpub","beskrivning":"Kårspexpub","tag":"other","datum":"10/4","time":{"start":1270850400000,"end":1270936800000},"day":{"start":221,"end":221}},{"raw":"16/4-18/4 Turné till Falun","beskrivning":"Turné till Falun","tag":"tour","datum":"16/4-18/4","time":{"start":1271368800000,"end":1271628000000},"day":{"start":227,"end":229}},{"raw":"17/4 Föreställning Falun","beskrivning":"Föreställning Falun","tag":"show","datum":"17/4","time":{"start":1271455200000,"end":1271541600000},"day":{"start":228,"end":228}},{"raw":"3/5 Omgång 3 på Södra teatern","beskrivning":"Omgång 3 på Södra teatern","tag":"show","datum":"3/5","time":{"start":1272837600000,"end":1272924000000},"day":{"start":244,"end":244}},{"raw":"4/5 Omgång 3 på Södra teatern","beskrivning":"Omgång 3 på Södra teatern","tag":"show","datum":"4/5","time":{"start":1272924000000,"end":1273010400000},"day":{"start":245,"end":245}},{"raw":"5/5 Slaskföreställning","beskrivning":"Slaskföreställning","tag":"show","datum":"5/5","time":{"start":1273010400000,"end":1273096800000},"day":{"start":246,"end":246}},{"raw":"7/5 Gamla spexare-fest","beskrivning":"Gamla spexare-fest","tag":"party","datum":"7/5","time":{"start":1273183200000,"end":1273269600000},"day":{"start":248,"end":248}},{"raw":"5/6-6/6 Marfan","beskrivning":"Marfan","tag":"tour","datum":"5/6-6/6","time":{"start":1275688800000,"end":1275861600000},"day":{"start":277,"end":278}},{"raw":"5/6 Föreställning Marfan","beskrivning":"Föreställning Marfan","tag":"show","datum":"5/6","time":{"start":1275688800000,"end":1275775200000},"day":{"start":277,"end":277}},{"raw":"13/6 Tennstopet","beskrivning":"Tennstopet","tag":"other","datum":"13/6","time":{"start":1276380000000,"end":1276466400000},"day":{"start":285,"end":285}},{"raw":"30/8 N0lleföreställningar och Externa relationer","beskrivning":"N0lleföreställningar och Externa relationer","tag":"show","datum":"30/8","time":{"start":1283119200000,"end":1283205600000},"day":{"start":363,"end":363}},{"raw":"31/8 N0lleföreställningar och Externa relationer","beskrivning":"N0lleföreställningar och Externa relationer","tag":"show","datum":"31/8","time":{"start":1283205600000,"end":1283292000000},"day":{"start":364,"end":364}},{"raw":"1/9 N0lleföreställningar och Externa relationer","beskrivning":"N0lleföreställningar och Externa relationer","tag":"show","datum":"1/9","time":{"start":1283292000000,"end":1283378400000},"day":{"start":365,"end":365}},{"raw":"4/9 Slutfest","beskrivning":"Slutfest","tag":"party","datum":"4/9","time":{"start":1283551200000,"end":1283637600000},"day":{"start":368,"end":368}}]},{"year":2010,"time":1283292000000,"data":[{"raw":"7/9 Kollationering","beskrivning":"Kollationering","tag":"meeting","datum":"7/9","time":{"start":1283810400000,"end":1283896800000},"day":{"start":6,"end":6}},{"raw":"17/9-19/9 Internat, Barnens ö, avfärd 17.05 från teknis = FEST!","beskrivning":"Internat, Barnens ö, avfärd 17.05 från teknis = FEST!","tag":"tour","datum":"17/9-19/9","time":{"start":1284674400000,"end":1284933600000},"day":{"start":16,"end":18}},{"raw":"2/10 Happening, ljusgården Teknikringen 78 och FEST!","beskrivning":"Happening, ljusgården Teknikringen 78 och FEST!","tag":"rehearsal","datum":"2/10","time":{"start":1285970400000,"end":1286056800000},"day":{"start":31,"end":31}},{"raw":"6/11 Smygis, Årsta folkets hus och FEST!","beskrivning":"Smygis, Årsta folkets hus och FEST!","tag":"rehearsal","datum":"6/11","time":{"start":1288998000000,"end":1289084400000},"day":{"start":66.04166666666667,"end":66.04166666666667}},{"raw":"7/11 Affeafton","beskrivning":"Affeafton","tag":"other","datum":"7/11","time":{"start":1289084400000,"end":1289170800000},"day":{"start":67.04166666666667,"end":67.04166666666667}},{"raw":"8/11 Biljettsläpp","beskrivning":"Biljettsläpp","tag":"other","datum":"8/11","time":{"start":1289170800000,"end":1289257200000},"day":{"start":68.04166666666667,"end":68.04166666666667}},{"raw":"29/11 Genrep, Södra teatern","beskrivning":"Genrep, Södra teatern","tag":"show","datum":"29/11","time":{"start":1290988800000,"end":1291075200000},"day":{"start":89.08333333333333,"end":89.08333333333333}},{"raw":"30/11 Premiärföreställning, Södra teatern och FEST!","beskrivning":"Premiärföreställning, Södra teatern och FEST!","tag":"show","datum":"30/11","time":{"start":1291075200000,"end":1291161600000},"day":{"start":90.08333333333333,"end":90.08333333333333}},{"raw":"1/12 Föreställning, Södra teatern","beskrivning":"Föreställning, Södra teatern","tag":"show","datum":"1/12","time":{"start":1291158000000,"end":1291244400000},"day":{"start":91.04166666666667,"end":91.04166666666667}},{"raw":"4/12 FEST!","beskrivning":"FEST!","tag":"party","datum":"4/12","time":{"start":1291417200000,"end":1291503600000},"day":{"start":94.04166666666667,"end":94.04166666666667}},{"raw":"6/12 Höstmöte","beskrivning":"Höstmöte","tag":"meeting","datum":"6/12","time":{"start":1291590000000,"end":1291676400000},"day":{"start":96.04166666666667,"end":96.04166666666667}},{"raw":"13/12 Spexluciabastu","beskrivning":"Spexluciabastu","tag":"other","datum":"13/12","time":{"start":1292198400000,"end":1292284800000},"day":{"start":103.08333333333333,"end":103.08333333333333}},{"raw":"4/2-8/2 Finlandsturné","beskrivning":"Finlandsturné","tag":"tour","datum":"4/2-8/2","time":{"start":1296774000000,"end":1297206000000},"day":{"start":156.04166666666666,"end":160.04166666666666}},{"raw":"6/2 Föreställning, Gloria kl 16","beskrivning":"Föreställning, Gloria kl 16","tag":"show","datum":"6/2","time":{"start":1296946800000,"end":1297033200000},"day":{"start":158.04166666666666,"end":158.04166666666666}},{"raw":"1/3 Föreställning, Intiman kl 19","beskrivning":"Föreställning, Intiman kl 19","tag":"show","datum":"1/3","time":{"start":1298934000000,"end":1299020400000},"day":{"start":181.04166666666666,"end":181.04166666666666}},{"raw":"2/3 Bjupp, Intiman kl 19 + fest!","beskrivning":"Bjupp, Intiman kl 19 + fest!","tag":"show","datum":"2/3","time":{"start":1299020400000,"end":1299106800000},"day":{"start":182.04166666666666,"end":182.04166666666666}},{"raw":"3/3 KTH-anställda, Intiman kl 19","beskrivning":"KTH-anställda, Intiman kl 19","tag":"show","datum":"3/3","time":{"start":1299106800000,"end":1299193200000},"day":{"start":183.04166666666666,"end":183.04166666666666}},{"raw":"27/2 Lackning av programblad, Kåren","beskrivning":"Lackning av programblad, Kåren","tag":"other","datum":"27/2","time":{"start":1298761200000,"end":1298847600000},"day":{"start":179.04166666666666,"end":179.04166666666666}},{"raw":"7/3 Hemsidesbludder","beskrivning":"Hemsidesbludder","tag":"other","datum":"7/3","time":{"start":1299452400000,"end":1299538800000},"day":{"start":187.04166666666666,"end":187.04166666666666}},{"raw":"11/3 Slaskfest med bastu","beskrivning":"Slaskfest med bastu","tag":"other","datum":"11/3","time":{"start":1299798000000,"end":1299884400000},"day":{"start":191.04166666666666,"end":191.04166666666666}},{"raw":"8/4-10/4 Karlstadsturné","beskrivning":"Karlstadsturné","tag":"tour","datum":"8/4-10/4","time":{"start":1302213600000,"end":1302472800000},"day":{"start":219,"end":221}},{"raw":"9/4 Föreställning, Arenan","beskrivning":"Föreställning, Arenan","tag":"show","datum":"9/4","time":{"start":1302300000000,"end":1302386400000},"day":{"start":220,"end":220}},{"raw":"2/5 Omgång 3, Södra teatern","beskrivning":"Omgång 3, Södra teatern","tag":"show","datum":"2/5","time":{"start":1304287200000,"end":1304373600000},"day":{"start":243,"end":243}},{"raw":"3/5 Gamla spexare-föreställning","beskrivning":"Gamla spexare-föreställning","tag":"show","datum":"3/5","time":{"start":1304373600000,"end":1304460000000},"day":{"start":244,"end":244}},{"raw":"4/5 Omgång 3, Södra teatern","beskrivning":"Omgång 3, Södra teatern","tag":"show","datum":"4/5","time":{"start":1304460000000,"end":1304546400000},"day":{"start":245,"end":245}},{"raw":"6/5 Gamla spexare-fest","beskrivning":"Gamla spexare-fest","tag":"party","datum":"6/5","time":{"start":1304632800000,"end":1304719200000},"day":{"start":247,"end":247}},{"raw":"14/5 Quarnevalen","beskrivning":"Quarnevalen","tag":"other","datum":"14/5","time":{"start":1305324000000,"end":1305410400000},"day":{"start":255,"end":255}},{"raw":"21/5 Slaskfest","beskrivning":"Slaskfest","tag":"party","datum":"21/5","time":{"start":1305928800000,"end":1306015200000},"day":{"start":262,"end":262}},{"raw":"5/6 kl 13 Tennstopet","beskrivning":"kl 13 Tennstopet","tag":"other","datum":"5/6","time":{"start":1307224800000,"end":1307311200000},"day":{"start":277,"end":277}},{"raw":"11/6 Mariefredsturné","beskrivning":"Mariefredsturné","tag":"tour","datum":"11/6","time":{"start":1307743200000,"end":1307829600000},"day":{"start":283,"end":283}},{"raw":"28/8 slaskföreställning prel kl 16(obs! på en söndag)","beskrivning":"slaskföreställning prel kl 16(obs! på en söndag)","tag":"show","datum":"28/8","time":{"start":1314482400000,"end":1314568800000},"day":{"start":361,"end":361}},{"raw":"29/8 n0lleföreställning kl 18.30","beskrivning":"n0lleföreställning kl 18.30","tag":"show","datum":"29/8","time":{"start":1314568800000,"end":1314655200000},"day":{"start":362,"end":362}},{"raw":"30/8 KTH Alumni kl 19","beskrivning":"KTH Alumni kl 19","tag":"show","datum":"30/8","time":{"start":1314655200000,"end":1314741600000},"day":{"start":363,"end":363}},{"raw":"31/8 n0lleföreställning kl 18.30","beskrivning":"n0lleföreställning kl 18.30","tag":"show","datum":"31/8","time":{"start":1314741600000,"end":1314828000000},"day":{"start":364,"end":364}},{"raw":"3/9 Slutfest","beskrivning":"Slutfest","tag":"party","datum":"3/9","time":{"start":1315000800000,"end":1315087200000},"day":{"start":367,"end":367}}]},{"year":2011,"time":1314828000000,"data":[{"raw":"8/9 Kollationering","beskrivning":"Kollationering","tag":"meeting","datum":"8/9","time":{"start":1315432800000,"end":1315519200000},"day":{"start":7,"end":7}},{"raw":"16/9-18/9 Internat","beskrivning":"Internat","tag":"tour","datum":"16/9-18/9","time":{"start":1316124000000,"end":1316383200000},"day":{"start":15,"end":17}},{"raw":"8/10 Happening","beskrivning":"Happening","tag":"rehearsal","datum":"8/10","time":{"start":1318024800000,"end":1318111200000},"day":{"start":37,"end":37}},{"raw":"27/10 Biljettsläpp till årets premiär och omgång 1. Och PR-bludder 2!!","beskrivning":"Biljettsläpp till årets premiär och omgång 1. Och PR-bludder 2!!","tag":"other","datum":"27/10","time":{"start":1319673600000,"end":1319760000000},"day":{"start":56.083333333333336,"end":56.083333333333336}},{"raw":"5/11 Smygis Bristol, Sundbyberg","beskrivning":"Smygis Bristol, Sundbyberg","tag":"rehearsal","datum":"5/11","time":{"start":1320447600000,"end":1320534000000},"day":{"start":65.04166666666667,"end":65.04166666666667}},{"raw":"12/11 Shoppingtur för inköp av premiärkläder","beskrivning":"Shoppingtur för inköp av premiärkläder","tag":"other","datum":"12/11","time":{"start":1321056000000,"end":1321142400000},"day":{"start":72.08333333333333,"end":72.08333333333333}},{"raw":"25/11 När det bara är några dagar kvar inför premiären så behöver man en paus så därför är det Qlubb M igen! Mer info kommer.","beskrivning":"När det bara är några dagar kvar inför premiären så behöver man en paus så därför är det Qlubb M igen! Mer info kommer.","tag":"other","datum":"25/11","time":{"start":1322179200000,"end":1322265600000},"day":{"start":85.08333333333333,"end":85.08333333333333}},{"raw":"28/11 Genrep","beskrivning":"Genrep","tag":"show","datum":"28/11","time":{"start":1322438400000,"end":1322524800000},"day":{"start":88.08333333333333,"end":88.08333333333333}},{"raw":"29/11 Premiär","beskrivning":"Premiär","tag":"show","datum":"29/11","time":{"start":1322524800000,"end":1322611200000},"day":{"start":89.08333333333333,"end":89.08333333333333}},{"raw":"30/11 Föreställning","beskrivning":"Föreställning","tag":"show","datum":"30/11","time":{"start":1322611200000,"end":1322697600000},"day":{"start":90.08333333333333,"end":90.08333333333333}},{"raw":"7/12 L1 Stormöte med info om Spex-SM","beskrivning":"L1 Stormöte med info om Spex-SM","tag":"meeting","datum":"7/12","time":{"start":1323212400000,"end":1323298800000},"day":{"start":97.04166666666667,"end":97.04166666666667}},{"raw":"20/1: Premiärslask","beskrivning":"Premiärslask","tag":"party","datum":"20/1","time":{"start":1327014000000,"end":1327100400000},"day":{"start":141.04166666666666,"end":141.04166666666666}},{"raw":"26/1-30/1: FINLAND!!!","beskrivning":"FINLAND!!!","tag":"tour","datum":"26/1-30/1","time":{"start":1327532400000,"end":1327964400000},"day":{"start":147.04166666666666,"end":151.04166666666666}},{"raw":"28/1 Föreställning Finland","beskrivning":"Föreställning Finland","tag":"show","datum":"28/1","time":{"start":1327705200000,"end":1327791600000},"day":{"start":149.04166666666666,"end":149.04166666666666}},{"raw":"13/2-15/2: Omgång 2. Bjupp (med fest efteråt på natten)","beskrivning":"Omgång 2. Bjupp (med fest efteråt på natten)","tag":"show","datum":"13/2-15/2","time":{"start":1329087600000,"end":1329346800000},"day":{"start":165.04166666666666,"end":167.04166666666666}},{"raw":"13/2-15/2: Omgång 2. Tisdag: KTH-anställda","beskrivning":"Omgång 2. Tisdag: KTH-anställda","tag":"show","datum":"13/2-15/2","time":{"start":1329087600000,"end":1329346800000},"day":{"start":165.04166666666666,"end":167.04166666666666}},{"raw":"13/2-15/2: Omgång 2. Onsdag: Som ”vanligt” (även om det inte finns något vanligt med en underbar Kårspex-föreställning)","beskrivning":"Omgång 2. Onsdag: Som ”vanligt” (även om det inte finns något vanligt med en underbar Kårspex-föreställning)","tag":"show","datum":"13/2-15/2","time":{"start":1329087600000,"end":1329346800000},"day":{"start":165.04166666666666,"end":167.04166666666666}},{"raw":"21/3 Vårmöte","beskrivning":"Vårmöte","tag":"meeting","datum":"21/3","time":{"start":1332284400000,"end":1332370800000},"day":{"start":202.04166666666666,"end":202.04166666666666}},{"raw":"2/4: Omgång 3","beskrivning":"Omgång 3","tag":"show","datum":"2/4","time":{"start":1333317600000,"end":1333404000000},"day":{"start":214,"end":214}},{"raw":"3/4: Omgång 3","beskrivning":"Omgång 3","tag":"show","datum":"3/4","time":{"start":1333404000000,"end":1333490400000},"day":{"start":215,"end":215}},{"raw":"4/4: Omgång 3","beskrivning":"Omgång 3","tag":"show","datum":"4/4","time":{"start":1333490400000,"end":1333576800000},"day":{"start":216,"end":216}},{"raw":"14/4: Gamla Spexare-festen","beskrivning":"Gamla Spexare-festen","tag":"party","datum":"14/4","time":{"start":1334354400000,"end":1334440800000},"day":{"start":226,"end":226}},{"raw":"13/5: Genrep Spex-SM","beskrivning":"Genrep Spex-SM","tag":"rehearsal","datum":"13/5","time":{"start":1336860000000,"end":1336946400000},"day":{"start":255,"end":255}},{"raw":"17/5-20/5: Spex-SM","beskrivning":"Spex-SM","tag":"tour","datum":"17/5-20/5","time":{"start":1337205600000,"end":1337551200000},"day":{"start":259,"end":262}},{"raw":"17/5: Föreställning Spex-SM","beskrivning":"Föreställning Spex-SM","tag":"show","datum":"17/5","time":{"start":1337205600000,"end":1337292000000},"day":{"start":259,"end":259}},{"raw":"23/5: Spexinarium 2","beskrivning":"Spexinarium 2","tag":"other","datum":"23/5","time":{"start":1337724000000,"end":1337810400000},"day":{"start":265,"end":265}},{"raw":"9/6-10/6: Turné Marfan","beskrivning":"Turné Marfan","tag":"tour","datum":"9/6-10/6","time":{"start":1339192800000,"end":1339365600000},"day":{"start":282,"end":283}},{"raw":"9/6 Föreställning Marfan","beskrivning":"Föreställning Marfan","tag":"show","datum":"9/6","time":{"start":1339192800000,"end":1339279200000},"day":{"start":282,"end":282}},{"raw":"26/8: Slask föreställningsstart kl 16","beskrivning":"Slask föreställningsstart kl 16","tag":"show","datum":"26/8","time":{"start":1345932000000,"end":1346018400000},"day":{"start":360,"end":360}},{"raw":"27/8: n0llan","beskrivning":"n0llan","tag":"show","datum":"27/8","time":{"start":1346018400000,"end":1346104800000},"day":{"start":361,"end":361}},{"raw":"29/8: n0llan","beskrivning":"n0llan","tag":"show","datum":"29/8","time":{"start":1346191200000,"end":1346277600000},"day":{"start":363,"end":363}},{"raw":"30/8: KTH alumni","beskrivning":"KTH alumni","tag":"show","datum":"30/8","time":{"start":1346277600000,"end":1346364000000},"day":{"start":364,"end":364}},{"raw":"8/9 Slutfest","beskrivning":"Slutfest","tag":"party","datum":"8/9","time":{"start":1347055200000,"end":1347141600000},"day":{"start":373,"end":373}}]},{"year":2012,"time":1346450400000,"data":[{"raw":"4/9 - Kollationering","beskrivning":"Kollationering","tag":"meeting","datum":"4/9","time":{"start":1346709600000,"end":1346796000000},"day":{"start":3,"end":3}},{"raw":"14/9-16/9 - Internatet","beskrivning":"Internatet","tag":"tour","datum":"14/9-16/9","time":{"start":1347573600000,"end":1347832800000},"day":{"start":13,"end":15}},{"raw":"29/9 - Happening","beskrivning":"Happening","tag":"rehearsal","datum":"29/9","time":{"start":1348869600000,"end":1348956000000},"day":{"start":28,"end":28}},{"raw":"30/10 - TF's (TeknologFöreningen i Finlands) spex kommer till Stockholm och spelar","beskrivning":"TF's (TeknologFöreningen i Finlands) spex kommer till Stockholm och spelar","tag":"other","datum":"30/10","time":{"start":1351555200000,"end":1351641600000},"day":{"start":59.083333333333336,"end":59.083333333333336}},{"raw":"3/11 - Smygis","beskrivning":"Smygis","tag":"rehearsal","datum":"3/11","time":{"start":1351897200000,"end":1351983600000},"day":{"start":63.041666666666664,"end":63.041666666666664}},{"raw":"23/11 - Slaskfest","beskrivning":"Slaskfest","tag":"party","datum":"23/11","time":{"start":1353628800000,"end":1353715200000},"day":{"start":83.08333333333333,"end":83.08333333333333}},{"raw":"4/12 - Höstmöte (stormöte där vi bland annat formellt avslutar spexåret 11/12 och avslöjar en plan för manus nästa år)","beskrivning":"Höstmöte (stormöte där vi bland annat formellt avslutar spexåret 11/12 och avslöjar en plan för manus nästa år)","tag":"meeting","datum":"4/12","time":{"start":1354575600000,"end":1354662000000},"day":{"start":94.04166666666667,"end":94.04166666666667}},{"raw":"19/1 - Sneakys","beskrivning":"Sneakys","tag":"rehearsal","datum":"19/1","time":{"start":1358550000000,"end":1358636400000},"day":{"start":140.04166666666666,"end":140.04166666666666}},{"raw":"30/1 - Genomdrag","beskrivning":"Genomdrag","tag":"show","datum":"30/1","time":{"start":1359500400000,"end":1359586800000},"day":{"start":151.04166666666666,"end":151.04166666666666}},{"raw":"31/1-4/2 - Finland","beskrivning":"Finland","tag":"tour","datum":"31/1-4/2","time":{"start":1359586800000,"end":1360018800000},"day":{"start":152.04166666666666,"end":156.04166666666666}},{"raw":"2/2 - Föreställning Finland","beskrivning":"Föreställning Finland","tag":"show","datum":"2/2","time":{"start":1359759600000,"end":1359846000000},"day":{"start":154.04166666666666,"end":154.04166666666666}},{"raw":"4/2 - Spexinarium Acapellaperformance","beskrivning":"Spexinarium Acapellaperformance","tag":"other","datum":"4/2","time":{"start":1359932400000,"end":1360018800000},"day":{"start":156.04166666666666,"end":156.04166666666666}},{"raw":"1/3 - Genrep/Smygpremiär","beskrivning":"Genrep/Smygpremiär","tag":"show","datum":"1/3","time":{"start":1362092400000,"end":1362178800000},"day":{"start":181.04166666666666,"end":181.04166666666666}},{"raw":"2/3 - Premiär och Premiärfest","beskrivning":"Premiär och Premiärfest","tag":"show","datum":"2/3","time":{"start":1362178800000,"end":1362265200000},"day":{"start":182.04166666666666,"end":182.04166666666666}},{"raw":"3/3 - Föreställning","beskrivning":"Föreställning","tag":"show","datum":"3/3","time":{"start":1362265200000,"end":1362351600000},"day":{"start":183.04166666666666,"end":183.04166666666666}},{"raw":"16/3 - Slaskfest","beskrivning":"Slaskfest","tag":"party","datum":"16/3","time":{"start":1363388400000,"end":1363474800000},"day":{"start":196.04166666666666,"end":196.04166666666666}},{"raw":"21/3 - Vårmöte med val av nya directionen och ny revisor","beskrivning":"Vårmöte med val av nya directionen och ny revisor","tag":"meeting","datum":"21/3","time":{"start":1363820400000,"end":1363906800000},"day":{"start":201.04166666666666,"end":201.04166666666666}},{"raw":"5/5 - Gamla spexareföreställning","beskrivning":"Gamla spexareföreställning","tag":"show","datum":"5/5","time":{"start":1367704800000,"end":1367791200000},"day":{"start":246,"end":246}},{"raw":"6/5 - Bjuppföreställning och eventuellt pub","beskrivning":"Bjuppföreställning och eventuellt pub","tag":"show","datum":"6/5","time":{"start":1367791200000,"end":1367877600000},"day":{"start":247,"end":247}},{"raw":"7/5 - KTH-anställda","beskrivning":"KTH-anställda","tag":"show","datum":"7/5","time":{"start":1367877600000,"end":1367964000000},"day":{"start":248,"end":248}},{"raw":"11/5 - Gamla spexarefest","beskrivning":"Gamla spexarefest","tag":"party","datum":"11/5","time":{"start":1368223200000,"end":1368309600000},"day":{"start":252,"end":252}},{"raw":"18/5 - Föreställning av LiSS och slaskfest med LiSS","beskrivning":"Föreställning av LiSS och slaskfest med LiSS","tag":"other","datum":"18/5","time":{"start":1368828000000,"end":1368914400000},"day":{"start":259,"end":259}},{"raw":"1/6-2/6 - Marfan (turné till Mariefred)","beskrivning":"Marfan (turné till Mariefred)","tag":"tour","datum":"1/6-2/6","time":{"start":1370037600000,"end":1370210400000},"day":{"start":273,"end":274}},{"raw":"1/6 Föreställning Marfan","beskrivning":"Föreställning Marfan","tag":"show","datum":"1/6","time":{"start":1370037600000,"end":1370124000000},"day":{"start":273,"end":273}},{"raw":"5/6-9/6 - Turné till Småland och Lund","beskrivning":"Turné till Småland och Lund","tag":"tour","datum":"5/6-9/6","time":{"start":1370383200000,"end":1370815200000},"day":{"start":277,"end":281}},{"raw":"6/6 - Föreställning Åseda","beskrivning":"Föreställning Åseda","tag":"show","datum":"6/6","time":{"start":1370469600000,"end":1370556000000},"day":{"start":278,"end":278}},{"raw":"8/6 - Föreställning Lund","beskrivning":"Föreställning Lund","tag":"show","datum":"8/6","time":{"start":1370642400000,"end":1370728800000},"day":{"start":280,"end":280}},{"raw":"21/8 - Slaskföreställning","beskrivning":"Slaskföreställning","tag":"show","datum":"21/8","time":{"start":1377036000000,"end":1377122400000},"day":{"start":354,"end":354}},{"raw":"22/8 - Föreställning KTH externa relationer","beskrivning":"Föreställning KTH externa relationer","tag":"show","datum":"22/8","time":{"start":1377122400000,"end":1377208800000},"day":{"start":355,"end":355}},{"raw":"2/9 - n0lleföreställning","beskrivning":"n0lleföreställning","tag":"show","datum":"2/9","time":{"start":1378072800000,"end":1378159200000},"day":{"start":366,"end":366}},{"raw":"4/9 - n0lleföreställning","beskrivning":"n0lleföreställning","tag":"show","datum":"4/9","time":{"start":1378245600000,"end":1378332000000},"day":{"start":368,"end":368}},{"raw":"6/9 Slutfest","beskrivning":"Slutfest","tag":"party","datum":"6/9","time":{"start":1378418400000,"end":1378504800000},"day":{"start":370,"end":370}}]},{"year":2013,"time":1377986400000,"data":[{"raw":"11/9 Kollationering","beskrivning":"Kollationering","tag":"meeting","datum":"11/9","time":{"start":1378850400000,"end":1378936800000},"day":{"start":10,"end":10}},{"raw":"20/9-22/9 Internat på Barnens ö","beskrivning":"Internat på Barnens ö","tag":"tour","datum":"20/9-22/9","time":{"start":1379628000000,"end":1379887200000},"day":{"start":19,"end":21}},{"raw":"12/10 Happening","beskrivning":"Happening","tag":"rehearsal","datum":"12/10","time":{"start":1381536000000,"end":1381622400000},"day":{"start":41.083333333333336,"end":41.083333333333336}},{"raw":"9/11 Smygis, Teater Bristol, Sundbyberg","beskrivning":"Smygis, Teater Bristol, Sundbyberg","tag":"rehearsal","datum":"9/11","time":{"start":1383951600000,"end":1384038000000},"day":{"start":69.04166666666667,"end":69.04166666666667}},{"raw":"13/11 Höstmöte","beskrivning":"Höstmöte","tag":"meeting","datum":"13/11","time":{"start":1384300800000,"end":1384387200000},"day":{"start":73.08333333333333,"end":73.08333333333333}},{"raw":"5/12 Genrep, Södra Teatern","beskrivning":"Genrep, Södra Teatern","tag":"show","datum":"5/12","time":{"start":1386198000000,"end":1386284400000},"day":{"start":95.04166666666667,"end":95.04166666666667}},{"raw":"8/12 Premiär, Södra Teatern","beskrivning":"Premiär, Södra Teatern","tag":"show","datum":"8/12","time":{"start":1386457200000,"end":1386543600000},"day":{"start":98.04166666666667,"end":98.04166666666667}},{"raw":"9/12 Föreställning, Södra Teatern","beskrivning":"Föreställning, Södra Teatern","tag":"show","datum":"9/12","time":{"start":1386543600000,"end":1386630000000},"day":{"start":99.04166666666667,"end":99.04166666666667}},{"raw":"6/2-9/2 Finlandsturné","beskrivning":"Finlandsturné","tag":"tour","datum":"6/2-9/2","time":{"start":1391641200000,"end":1391986800000},"day":{"start":158.04166666666666,"end":161.04166666666666}},{"raw":"8/2 Föreställning Finland","beskrivning":"Föreställning Finland","tag":"show","datum":"8/2","time":{"start":1391814000000,"end":1391900400000},"day":{"start":160.04166666666666,"end":160.04166666666666}},{"raw":"16/2 Omgång 2, Södran","beskrivning":"Omgång 2, Södran","tag":"show","datum":"16/2","time":{"start":1392505200000,"end":1392591600000},"day":{"start":168.04166666666666,"end":168.04166666666666}},{"raw":"17/2 Omgång 2, Södran","beskrivning":"Omgång 2, Södran","tag":"show","datum":"17/2","time":{"start":1392591600000,"end":1392678000000},"day":{"start":169.04166666666666,"end":169.04166666666666}},{"raw":"18/2 Omgång 2, Södran","beskrivning":"Omgång 2, Södran","tag":"show","datum":"18/2","time":{"start":1392678000000,"end":1392764400000},"day":{"start":170.04166666666666,"end":170.04166666666666}},{"raw":"24/3: Omgång 3","beskrivning":"Omgång 3","tag":"show","datum":"24/3","time":{"start":1395615600000,"end":1395702000000},"day":{"start":204.04166666666666,"end":204.04166666666666}},{"raw":"25/3: Omgång 3","beskrivning":"Omgång 3","tag":"show","datum":"25/3","time":{"start":1395702000000,"end":1395788400000},"day":{"start":205.04166666666666,"end":205.04166666666666}},{"raw":"26/3: Omgång 3","beskrivning":"Omgång 3","tag":"show","datum":"26/3","time":{"start":1395788400000,"end":1395874800000},"day":{"start":206.04166666666666,"end":206.04166666666666}},{"raw":"29/3: Gamla spexare-festen","beskrivning":"Gamla spexare-festen","tag":"party","datum":"29/3","time":{"start":1396047600000,"end":1396134000000},"day":{"start":209.04166666666666,"end":209.04166666666666}},{"raw":"2/4: Vårmöte","beskrivning":"Vårmöte","tag":"meeting","datum":"2/4","time":{"start":1396389600000,"end":1396476000000},"day":{"start":213,"end":213}},{"raw":"3/5-10/5: Quarnevalen","beskrivning":"Quarnevalen","tag":"other","datum":"3/5-10/5","time":{"start":1399068000000,"end":1399759200000},"day":{"start":244,"end":251}},{"raw":"17/5-18/5: Osqvik","beskrivning":"Osqvik","tag":"party","datum":"17/5-18/5","time":{"start":1400277600000,"end":1400450400000},"day":{"start":258,"end":259}},{"raw":"31/8 Sista öppna föreställningen (sälj sälj sälj!). Tidig samling på teatern.","beskrivning":"Sista öppna föreställningen (sälj sälj sälj!). Tidig samling på teatern.","tag":"show","datum":"31/8","time":{"start":1409436000000,"end":1409522400000},"day":{"start":364,"end":364}},{"raw":"1/8 n0lleföreställning, köpt av KTH för n0llan. Samling nån gång efter lunch","beskrivning":"n0lleföreställning, köpt av KTH för n0llan. Samling nån gång efter lunch","tag":"show","datum":"1/8","time":{"start":1406844000000,"end":1406930400000},"day":{"start":334,"end":334}},{"raw":"2/8 Föreställning abonnerad av KTHs externa relationer. Samling nån gång efter lunch","beskrivning":"Föreställning abonnerad av KTHs externa relationer. Samling nån gång efter lunch","tag":"show","datum":"2/8","time":{"start":1406930400000,"end":1407016800000},"day":{"start":335,"end":335}},{"raw":"3/8 n0lleföreställning, köpt av KTH för n0llan. Samling nån gång efter lunch","beskrivning":"n0lleföreställning, köpt av KTH för n0llan. Samling nån gång efter lunch","tag":"show","datum":"3/8","time":{"start":1407016800000,"end":1407103200000},"day":{"start":336,"end":336}},{"raw":"13/9 Slutfest","beskrivning":"Slutfest","tag":"party","datum":"13/9","time":{"start":1410559200000,"end":1410645600000},"day":{"start":377,"end":377}}]},{"year":2014,"time":1409522400000,"data":[{"raw":"11/9 Kollationering","beskrivning":"Kollationering","tag":"meeting","datum":"11/9","time":{"start":1410386400000,"end":1410472800000},"day":{"start":10,"end":10}},{"raw":"19/9-21/9 Internat Barnens Ö","beskrivning":"Internat Barnens Ö","tag":"tour","datum":"19/9-21/9","time":{"start":1411077600000,"end":1411336800000},"day":{"start":18,"end":20}},{"raw":"1/10 PR-bludder. E36 18-21","beskrivning":"PR-bludder. E36 18-21","tag":"other","datum":"1/10","time":{"start":1412114400000,"end":1412200800000},"day":{"start":30,"end":30}},{"raw":"11/10 Happening SingSing. Campus KTH","beskrivning":"Happening SingSing. Campus KTH","tag":"rehearsal","datum":"11/10","time":{"start":1412985600000,"end":1413072000000},"day":{"start":40.083333333333336,"end":40.083333333333336}},{"raw":"22/10 PR-bludder följt av QlubbM, Radiorummet Kåren, QlubbM","beskrivning":"PR-bludder följt av QlubbM, Radiorummet Kåren, QlubbM","tag":"other","datum":"22/10","time":{"start":1413936000000,"end":1414022400000},"day":{"start":51.083333333333336,"end":51.083333333333336}},{"raw":"8/11 Smygis Berga teater. Åkersberga","beskrivning":"Smygis Berga teater. Åkersberga","tag":"rehearsal","datum":"8/11","time":{"start":1415401200000,"end":1415487600000},"day":{"start":68.04166666666667,"end":68.04166666666667}},{"raw":"14/11-16/11 Fondmålning. Övre Ateljén Arkitekthögskolan","beskrivning":"Fondmålning. Övre Ateljén Arkitekthögskolan","tag":"other","datum":"14/11-16/11","time":{"start":1415923200000,"end":1416182400000},"day":{"start":74.08333333333333,"end":76.08333333333333}},{"raw":"6/12 Sneakys, Riksteatern scen 2, Hallunda","beskrivning":"Sneakys, Riksteatern scen 2, Hallunda","tag":"rehearsal","datum":"6/12","time":{"start":1417820400000,"end":1417906800000},"day":{"start":96.04166666666667,"end":96.04166666666667}},{"raw":"8/12 18:30, Spexinarium Accapella Performance. E31","beskrivning":"18:30, Spexinarium Accapella Performance. E31","tag":"other","datum":"8/12","time":{"start":1417993200000,"end":1418079600000},"day":{"start":98.04166666666667,"end":98.04166666666667}},{"raw":"9/12 18:00, Höstmöte. D3","beskrivning":"18:00, Höstmöte. D3","tag":"meeting","datum":"9/12","time":{"start":1418079600000,"end":1418166000000},"day":{"start":99.04166666666667,"end":99.04166666666667}},{"raw":"5/2-9/2 Finlandsturné och ur-premiär","beskrivning":"Finlandsturné och ur-premiär","tag":"tour","datum":"5/2-9/2","time":{"start":1423090800000,"end":1423522800000},"day":{"start":157.04166666666666,"end":161.04166666666666}},{"raw":"7/2 Ur-premiär","beskrivning":"Ur-premiär","tag":"show","datum":"7/2","time":{"start":1423263600000,"end":1423350000000},"day":{"start":159.04166666666666,"end":159.04166666666666}},{"raw":"22/2 Omgång 1 och Sverige-premiär, Södran","beskrivning":"Omgång 1 och Sverige-premiär, Södran","tag":"show","datum":"22/2","time":{"start":1424559600000,"end":1424646000000},"day":{"start":174.04166666666666,"end":174.04166666666666}},{"raw":"23/2 Omgång 1 och Sverige-premiär, Södran","beskrivning":"Omgång 1 och Sverige-premiär, Södran","tag":"show","datum":"23/2","time":{"start":1424646000000,"end":1424732400000},"day":{"start":175.04166666666666,"end":175.04166666666666}},{"raw":"24/2 Omgång 1 och Sverige-premiär, Södran","beskrivning":"Omgång 1 och Sverige-premiär, Södran","tag":"show","datum":"24/2","time":{"start":1424732400000,"end":1424818800000},"day":{"start":176.04166666666666,"end":176.04166666666666}},{"raw":"25/3 Vårmöte, B1","beskrivning":"Vårmöte, B1","tag":"meeting","datum":"25/3","time":{"start":1427238000000,"end":1427324400000},"day":{"start":205.04166666666666,"end":205.04166666666666}},{"raw":"19/4 Omgång 2, Södran Gamla spexare","beskrivning":"Omgång 2, Södran Gamla spexare","tag":"show","datum":"19/4","time":{"start":1429394400000,"end":1429480800000},"day":{"start":230,"end":230}},{"raw":"20/4 Omgång 2, Södran Gamla spexare","beskrivning":"Omgång 2, Södran Gamla spexare","tag":"show","datum":"20/4","time":{"start":1429480800000,"end":1429567200000},"day":{"start":231,"end":231}},{"raw":"21/4 Omgång 2, Södran Gamla spexare","beskrivning":"Omgång 2, Södran Gamla spexare","tag":"show","datum":"21/4","time":{"start":1429567200000,"end":1429653600000},"day":{"start":232,"end":232}},{"raw":"13/5-17/5 Turné Linköping-Åseda","beskrivning":"Turné Linköping-Åseda","tag":"tour","datum":"13/5-17/5","time":{"start":1431468000000,"end":1431900000000},"day":{"start":254,"end":258}},{"raw":"14/5 Föreställning Linköping","beskrivning":"Föreställning Linköping","tag":"show","datum":"14/5","time":{"start":1431554400000,"end":1431640800000},"day":{"start":255,"end":255}},{"raw":"16/5 Föreställning Åseda","beskrivning":"Föreställning Åseda","tag":"show","datum":"16/5","time":{"start":1431727200000,"end":1431813600000},"day":{"start":257,"end":257}},{"raw":"6/6-7/6 Marfan, Mariefred","beskrivning":"Marfan, Mariefred","tag":"tour","datum":"6/6-7/6","time":{"start":1433541600000,"end":1433714400000},"day":{"start":278,"end":279}},{"raw":"6/6 Förestälnning Marfan","beskrivning":"Förestälnning Marfan","tag":"tour","datum":"6/6","time":{"start":1433541600000,"end":1433628000000},"day":{"start":278,"end":278}},{"raw":"31/8 n0lle","beskrivning":"n0lle","tag":"show","datum":"31/8","time":{"start":1440972000000,"end":1441058400000},"day":{"start":364,"end":364}},{"raw":"1/9 n0lle","beskrivning":"n0lle","tag":"show","datum":"1/9","time":{"start":1441058400000,"end":1441144800000},"day":{"start":365,"end":365}},{"raw":"2/9 n0lle","beskrivning":"n0lle","tag":"show","datum":"2/9","time":{"start":1441144800000,"end":1441231200000},"day":{"start":366,"end":366}}]},{"year":2015,"time":1441058400000,"data":[{"raw":"8/9 Kollationering (på Valhalla campus, L1)","beskrivning":"Kollationering (på Valhalla campus, L1)","tag":"meeting","datum":"8/9","time":{"start":1441663200000,"end":1441749600000},"day":{"start":7,"end":7}},{"raw":"18/9-20/9-sön  Internatet (Granö gård, Barnens Ö)","beskrivning":"Internatet (Granö gård, Barnens Ö)","tag":"tour","datum":"18/9-20/9","time":{"start":1442527200000,"end":1442786400000},"day":{"start":17,"end":19}},{"raw":"10/10   Happening","beskrivning":"Happening","tag":"meeting","datum":"10/10","time":{"start":1444435200000,"end":1444521600000},"day":{"start":39.083333333333336,"end":39.083333333333336}},{"raw":"17/10  Ev. Sittning med Teknologkören (och ev. PQ)","beskrivning":"Ev. Sittning med Teknologkören (och ev. PQ)","tag":"other","datum":"17/10","time":{"start":1445040000000,"end":1445126400000},"day":{"start":46.083333333333336,"end":46.083333333333336}},{"raw":"1/11 Filmkväll: VLF (Musikrummet) kl. 14:00","beskrivning":"Filmkväll: VLF (Musikrummet) kl. 14:00","tag":"other","datum":"1/11","time":{"start":1446332400000,"end":1446418800000},"day":{"start":61.041666666666664,"end":61.041666666666664}},{"raw":"14/11 Checkis + 100-klubbens afton","beskrivning":"Checkis + 100-klubbens afton","tag":"rehearsal","datum":"14/11","time":{"start":1447459200000,"end":1447545600000},"day":{"start":74.08333333333333,"end":74.08333333333333}},{"raw":"21/11-22/11-sön  Chalmerspexet Vera i Stockholm, ev. sittning tillsammans","beskrivning":"Chalmerspexet Vera i Stockholm, ev. sittning tillsammans","tag":"other","datum":"21/11-22/11","time":{"start":1448064000000,"end":1448236800000},"day":{"start":81.08333333333333,"end":82.08333333333333}},{"raw":"5/12 Sångartäflan","beskrivning":"Sångartäflan","tag":"other","datum":"5/12","time":{"start":1449270000000,"end":1449356400000},"day":{"start":95.04166666666667,"end":95.04166666666667}},{"raw":"6/12 Målardag med Tekniken","beskrivning":"Målardag med Tekniken","tag":"other","datum":"6/12","time":{"start":1449356400000,"end":1449442800000},"day":{"start":96.04166666666667,"end":96.04166666666667}},{"raw":"12/12 Smygis","beskrivning":"Smygis","tag":"rehearsal","datum":"12/12","time":{"start":1449878400000,"end":1449964800000},"day":{"start":102.08333333333333,"end":102.08333333333333}},{"raw":"16/12 Höstmöte","beskrivning":"Höstmöte","tag":"meeting","datum":"16/12","time":{"start":1450224000000,"end":1450310400000},"day":{"start":106.08333333333333,"end":106.08333333333333}},{"raw":"26/1 Genrep (Södra Teatern)","beskrivning":"Genrep (Södra Teatern)","tag":"show","datum":"26/1","time":{"start":1453762800000,"end":1453849200000},"day":{"start":147.04166666666666,"end":147.04166666666666}},{"raw":"27/1 Premiär (Södra Teatern)","beskrivning":"Premiär (Södra Teatern)","tag":"show","datum":"27/1","time":{"start":1453849200000,"end":1453935600000},"day":{"start":148.04166666666666,"end":148.04166666666666}},{"raw":"28/1 KTH-föreställning (Södra Teatern)","beskrivning":"KTH-föreställning (Södra Teatern)","tag":"show","datum":"28/1","time":{"start":1453935600000,"end":1454022000000},"day":{"start":149.04166666666666,"end":149.04166666666666}},{"raw":"30/1 ​Premiärfesten","beskrivning":"​Premiärfesten","tag":"party","datum":"30/1","time":{"start":1454108400000,"end":1454194800000},"day":{"start":151.04166666666666,"end":151.04166666666666}},{"raw":"18/2-21/2 Finlandsturné","beskrivning":"Finlandsturné","tag":"tour","datum":"18/2-21/2","time":{"start":1455750000000,"end":1456095600000},"day":{"start":170.04166666666666,"end":173.04166666666666}},{"raw":"20/2 Föreställning Finland","beskrivning":"Föreställning Finland","tag":"show","datum":"20/2","time":{"start":1455922800000,"end":1456009200000},"day":{"start":172.04166666666666,"end":172.04166666666666}},{"raw":"13/3 Omgång 2: Bjuppföreställning (Södra Teatern) + Bjuppfest (Stora gasque)","beskrivning":"Omgång 2: Bjuppföreställning (Södra Teatern) + Bjuppfest (Stora gasque)","tag":"show","datum":"13/3","time":{"start":1457823600000,"end":1457910000000},"day":{"start":194.04166666666666,"end":194.04166666666666}},{"raw":"14/3 Omgång 2: Föreställning (Södra Teatern)","beskrivning":"Omgång 2: Föreställning (Södra Teatern)","tag":"show","datum":"14/3","time":{"start":1457910000000,"end":1457996400000},"day":{"start":195.04166666666666,"end":195.04166666666666}},{"raw":"6/4 Vårmöte","beskrivning":"Vårmöte","tag":"meeting","datum":"6/4","time":{"start":1459893600000,"end":1459980000000},"day":{"start":218,"end":218}},{"raw":"10/4 Omgång 3: Gamla spexare föreställning (Södra Teatern)","beskrivning":"Omgång 3: Gamla spexare föreställning (Södra Teatern)","tag":"show","datum":"10/4","time":{"start":1460239200000,"end":1460325600000},"day":{"start":222,"end":222}},{"raw":"11/4 Omgång 3: KTH-föreställning (Södra Teatern)","beskrivning":"Omgång 3: KTH-föreställning (Södra Teatern)","tag":"show","datum":"11/4","time":{"start":1460325600000,"end":1460412000000},"day":{"start":223,"end":223}},{"raw":"12/4 Omgång 3: Föreställning (Södra Teatern)","beskrivning":"Omgång 3: Föreställning (Södra Teatern)","tag":"show","datum":"12/4","time":{"start":1460412000000,"end":1460498400000},"day":{"start":224,"end":224}},{"raw":"16/4 Gamla spexare festen (Alviks kulturhus)","beskrivning":"Gamla spexare festen (Alviks kulturhus)","tag":"party","datum":"16/4","time":{"start":1460757600000,"end":1460844000000},"day":{"start":228,"end":228}},{"raw":"20/4 Spexinarium i improvisation #1 (D32)","beskrivning":"Spexinarium i improvisation #1 (D32)","tag":"other","datum":"20/4","time":{"start":1461103200000,"end":1461189600000},"day":{"start":232,"end":232}},{"raw":"27/4 Spexinarium i improvisation #2 (D32)","beskrivning":"Spexinarium i improvisation #2 (D32)","tag":"other","datum":"27/4","time":{"start":1461708000000,"end":1461794400000},"day":{"start":239,"end":239}},{"raw":"4/5 Spexinarium i improvisation #2 (D32)","beskrivning":"Spexinarium i improvisation #2 (D32)","tag":"other","datum":"4/5","time":{"start":1462312800000,"end":1462399200000},"day":{"start":246,"end":246}},{"raw":"6/5 Sittning med Lulespexet (Stora gasque)","beskrivning":"Sittning med Lulespexet (Stora gasque)","tag":"other","datum":"6/5","time":{"start":1462485600000,"end":1462572000000},"day":{"start":248,"end":248}},{"raw":"13/5-15/5 Myshelg","beskrivning":"Myshelg","tag":"other","datum":"13/5-15/5","time":{"start":1463090400000,"end":1463349600000},"day":{"start":255,"end":257}},{"raw":"18/5 Marknadsföringsworkshop med PR (L22)","beskrivning":"Marknadsföringsworkshop med PR (L22)","tag":"other","datum":"18/5","time":{"start":1463522400000,"end":1463608800000},"day":{"start":260,"end":260}},{"raw":"4/6-5/6 Mariefredsturné","beskrivning":"Mariefredsturné","tag":"tour","datum":"4/6-5/6","time":{"start":1464991200000,"end":1465164000000},"day":{"start":277,"end":278}},{"raw":"4/6 Föreställning Mariefred","beskrivning":"Föreställning Mariefred","tag":"show","datum":"4/6","time":{"start":1464991200000,"end":1465077600000},"day":{"start":277,"end":277}},{"raw":"10/8 Affeafton","beskrivning":"Affeafton","tag":"other","datum":"10/8","time":{"start":1470780000000,"end":1470866400000},"day":{"start":344,"end":344}},{"raw":"14/8 Qulturpub","beskrivning":"Qulturpub","tag":"other","datum":"14/8","time":{"start":1471125600000,"end":1471212000000},"day":{"start":348,"end":348}},{"raw":"22/8 Kårens dag","beskrivning":"Kårens dag","tag":"other","datum":"22/8","time":{"start":1471816800000,"end":1471903200000},"day":{"start":356,"end":356}},{"raw":"28/8 Qulturpub","beskrivning":"Qulturpub","tag":"other","datum":"28/8","time":{"start":1472335200000,"end":1472421600000},"day":{"start":362,"end":362}},{"raw":"29/8 n0lleomgång: n0lleföreställning (Södra Teatern)","beskrivning":"n0lleomgång: n0lleföreställning (Södra Teatern)","tag":"show","datum":"29/8","time":{"start":1472421600000,"end":1472508000000},"day":{"start":363,"end":363}},{"raw":"30/8 n0lleomgång: slaskföreställning (Södra Teatern)","beskrivning":"n0lleomgång: slaskföreställning (Södra Teatern)","tag":"show","datum":"30/8","time":{"start":1472508000000,"end":1472594400000},"day":{"start":364,"end":364}},{"raw":"31/8 n0lleomgång: n0lleföreställning (Södra Teatern)","beskrivning":"n0lleomgång: n0lleföreställning (Södra Teatern)","tag":"show","datum":"31/8","time":{"start":1472594400000,"end":1472680800000},"day":{"start":365,"end":365}},{"raw":"9/9 Slutfest (Osqvik)","beskrivning":"Slutfest (Osqvik)","tag":"party","datum":"9/9","time":{"start":1473372000000,"end":1473458400000},"day":{"start":374,"end":374}}]},{"year":2016,"time":1472680800000,"data":[{"raw":"6/9 Kollationering","beskrivning":"Kollationering","tag":"meeting","datum":"6/9","time":{"start":1473112800000,"end":1473199200000},"day":{"start":5,"end":5}},{"raw":"16/9-18/9 Internat på Granö Gård, Barnens Ö","beskrivning":"Internat på Granö Gård, Barnens Ö","tag":"tour","datum":"16/9-18/9","time":{"start":1473976800000,"end":1474236000000},"day":{"start":15,"end":17}},{"raw":"1/10 Happening, Sing Sing","beskrivning":"Happening, Sing Sing","tag":"rehearsal","datum":"1/10","time":{"start":1475272800000,"end":1475359200000},"day":{"start":30,"end":30}},{"raw":"12/11 Checkis, Ekhammarscenen, Kungsängen","beskrivning":"Checkis, Ekhammarscenen, Kungsängen","tag":"rehearsal","datum":"12/11","time":{"start":1478908800000,"end":1478995200000},"day":{"start":72.08333333333333,"end":72.08333333333333}},{"raw":"10/12 Smygis DOCH + 100-klubbens afton Alvik","beskrivning":"Smygis DOCH + 100-klubbens afton Alvik","tag":"rehearsal","datum":"10/12","time":{"start":1481328000000,"end":1481414400000},"day":{"start":100.08333333333333,"end":100.08333333333333}},{"raw":"14/12 Höstmöte, L1 på Campus","beskrivning":"Höstmöte, L1 på Campus","tag":"meeting","datum":"14/12","time":{"start":1481673600000,"end":1481760000000},"day":{"start":104.08333333333333,"end":104.08333333333333}},{"raw":"29/1 Genrep (Södra Teatern)","beskrivning":"Genrep (Södra Teatern)","tag":"show","datum":"29/1","time":{"start":1485644400000,"end":1485730800000},"day":{"start":150.04166666666666,"end":150.04166666666666}},{"raw":"30/1 Premiär","beskrivning":"Premiär","tag":"show","datum":"30/1","time":{"start":1485730800000,"end":1485817200000},"day":{"start":151.04166666666666,"end":151.04166666666666}},{"raw":"31/1 Föreställning, KTH Alumni","beskrivning":"Föreställning, KTH Alumni","tag":"show","datum":"31/1","time":{"start":1485817200000,"end":1485903600000},"day":{"start":152.04166666666666,"end":152.04166666666666}},{"raw":"4/2 Premiärfesten, Årsta Folkets Hus","beskrivning":"Premiärfesten, Årsta Folkets Hus","tag":"party","datum":"4/2","time":{"start":1486162800000,"end":1486249200000},"day":{"start":156.04166666666666,"end":156.04166666666666}},{"raw":"23/2-27/2 Finland","beskrivning":"Finland","tag":"tour","datum":"23/2-27/2","time":{"start":1487804400000,"end":1488236400000},"day":{"start":175.04166666666666,"end":179.04166666666666}},{"raw":"25/2 Föreställning Finland","beskrivning":"Föreställning Finland","tag":"show","datum":"25/2","time":{"start":1487977200000,"end":1488063600000},"day":{"start":177.04166666666666,"end":177.04166666666666}},{"raw":"28/3 Omgång 2, föreställning, Bjupp (Södra Teatern)","beskrivning":"Omgång 2, föreställning, Bjupp (Södra Teatern)","tag":"show","datum":"28/3","time":{"start":1490652000000,"end":1490738400000},"day":{"start":208,"end":208}},{"raw":"29/3 Omgång 2, föreställning","beskrivning":"Omgång 2, föreställning","tag":"show","datum":"29/3","time":{"start":1490738400000,"end":1490824800000},"day":{"start":209,"end":209}},{"raw":"31/3 Bjuppfest, Kistan, Kista","beskrivning":"Bjuppfest, Kistan, Kista","tag":"party","datum":"31/3","time":{"start":1490911200000,"end":1490997600000},"day":{"start":211,"end":211}},{"raw":"5/4 Vårmöte, V3, Campus","beskrivning":"Vårmöte, V3, Campus","tag":"meeting","datum":"5/4","time":{"start":1491343200000,"end":1491429600000},"day":{"start":216,"end":216}},{"raw":"23/4 Omgång 3, föreställning, Gamla Spexare, (Södra Teatern)","beskrivning":"Omgång 3, föreställning, Gamla Spexare, (Södra Teatern)","tag":"show","datum":"23/4","time":{"start":1492898400000,"end":1492984800000},"day":{"start":234,"end":234}},{"raw":"24/4 Omgång 3, föreställning, KTH Anställda","beskrivning":"Omgång 3, föreställning, KTH Anställda","tag":"show","datum":"24/4","time":{"start":1492984800000,"end":1493071200000},"day":{"start":235,"end":235}},{"raw":"25/4 Omgång 3, föreställning","beskrivning":"Omgång 3, föreställning","tag":"show","datum":"25/4","time":{"start":1493071200000,"end":1493157600000},"day":{"start":236,"end":236}},{"raw":"29/4 Gamla Spexare-festen","beskrivning":"Gamla Spexare-festen","tag":"party","datum":"29/4","time":{"start":1493416800000,"end":1493503200000},"day":{"start":240,"end":240}},{"raw":"22/5 Extrainsatt stormöte, Musikrummet, Nymble","beskrivning":"Extrainsatt stormöte, Musikrummet, Nymble","tag":"meeting","datum":"22/5","time":{"start":1495404000000,"end":1495490400000},"day":{"start":263,"end":263}},{"raw":"25/5-28/5 Spex-SM, Örebro","beskrivning":"Spex-SM, Örebro","tag":"tour","datum":"25/5-28/5","time":{"start":1495663200000,"end":1496008800000},"day":{"start":266,"end":269}},{"raw":"10/6 Sommaravslutning","beskrivning":"Sommaravslutning","tag":"other","datum":"10/6","time":{"start":1497045600000,"end":1497132000000},"day":{"start":282,"end":282}},{"raw":"28/8 N0lle-föreställning, (Södra Teatern)","beskrivning":"N0lle-föreställning, (Södra Teatern)","tag":"show","datum":"28/8","time":{"start":1503871200000,"end":1503957600000},"day":{"start":361,"end":361}},{"raw":"29/8 Slask-föreställning, (öppen för allmänheten)","beskrivning":"Slask-föreställning, (öppen för allmänheten)","tag":"show","datum":"29/8","time":{"start":1503957600000,"end":1504044000000},"day":{"start":362,"end":362}},{"raw":"30/8 N0lle-föreställning","beskrivning":"N0lle-föreställning","tag":"show","datum":"30/8","time":{"start":1504044000000,"end":1504130400000},"day":{"start":363,"end":363}},{"raw":"9/9 Slutfest, Kröken","beskrivning":"Slutfest, Kröken","tag":"party","datum":"9/9","time":{"start":1504908000000,"end":1504994400000},"day":{"start":373,"end":373}}]},{"year":2017,"time":1504216800000,"data":[{"raw":"7/9   Kollationering","beskrivning":"Kollationering","tag":"meeting","datum":"7/9","time":{"start":1504735200000,"end":1504821600000},"day":{"start":6,"end":6}},{"raw":"22/9-24/9  Internat, Barnens Ö","beskrivning":"Internat, Barnens Ö","tag":"tour","datum":"22/9-24/9","time":{"start":1506031200000,"end":1506290400000},"day":{"start":21,"end":23}},{"raw":"25/9   Extrainsatt stormöte #3","beskrivning":"Extrainsatt stormöte #3","tag":"meeting","datum":"25/9","time":{"start":1506290400000,"end":1506376800000},"day":{"start":24,"end":24}},{"raw":"14/10    Happening + Happeningfest","beskrivning":"Happening + Happeningfest","tag":"rehearsal","datum":"14/10","time":{"start":1507939200000,"end":1508025600000},"day":{"start":43.083333333333336,"end":43.083333333333336}},{"raw":"31/10 Bludder #1","beskrivning":"Bludder #1","tag":"other","datum":"31/10","time":{"start":1509408000000,"end":1509494400000},"day":{"start":60.083333333333336,"end":60.083333333333336}},{"raw":"4/11    Qulturgasque","beskrivning":"Qulturgasque","tag":"party","datum":"4/11","time":{"start":1509750000000,"end":1509836400000},"day":{"start":64.04166666666667,"end":64.04166666666667}},{"raw":"25/11    Checkis + Checkisfest","beskrivning":"Checkis + Checkisfest","tag":"rehearsal","datum":"25/11","time":{"start":1511568000000,"end":1511654400000},"day":{"start":85.08333333333333,"end":85.08333333333333}},{"raw":"2/12-3/12   Fondmålning","beskrivning":"Fondmålning","tag":"other","datum":"2/12-3/12","time":{"start":1512169200000,"end":1512342000000},"day":{"start":92.04166666666667,"end":93.04166666666667}},{"raw":"6/12   Bludder #2","beskrivning":"Bludder #2","tag":"other","datum":"6/12","time":{"start":1512514800000,"end":1512601200000},"day":{"start":96.04166666666667,"end":96.04166666666667}},{"raw":"11/12   Höstmöte","beskrivning":"Höstmöte","tag":"meeting","datum":"11/12","time":{"start":1512950400000,"end":1513036800000},"day":{"start":101.08333333333333,"end":101.08333333333333}},{"raw":"16/12   Smygis + Smygisfest","beskrivning":"Smygis + Smygisfest","tag":"rehearsal","datum":"16/12","time":{"start":1513382400000,"end":1513468800000},"day":{"start":106.08333333333333,"end":106.08333333333333}},{"raw":"28/12   Förrådsflytt","beskrivning":"Förrådsflytt","tag":"other","datum":"28/12","time":{"start":1514419200000,"end":1514505600000},"day":{"start":118.08333333333333,"end":118.08333333333333}},{"raw":"29/1   Genrep. Omgång 1, Södra Teatern","beskrivning":"Genrep. Omgång 1, Södra Teatern","tag":"show","datum":"29/1","time":{"start":1517180400000,"end":1517266800000},"day":{"start":150.04166666666666,"end":150.04166666666666}},{"raw":"30/1   Föreställning, premiär. Omgång 1, Södra Teatern","beskrivning":"Föreställning, premiär. Omgång 1, Södra Teatern","tag":"show","datum":"30/1","time":{"start":1517266800000,"end":1517353200000},"day":{"start":151.04166666666666,"end":151.04166666666666}},{"raw":"31/1   Föreställning. Omgång 1, Södra Teatern","beskrivning":"Föreställning. Omgång 1, Södra Teatern","tag":"show","datum":"31/1","time":{"start":1517353200000,"end":1517439600000},"day":{"start":152.04166666666666,"end":152.04166666666666}},{"raw":"3/2   Premiärfest","beskrivning":"Premiärfest","tag":"party","datum":"3/2","time":{"start":1517612400000,"end":1517698800000},"day":{"start":155.04166666666666,"end":155.04166666666666}},{"raw":"8/2-12/2-mån Finland","beskrivning":"Finland","tag":"tour","datum":"8/2-12/2","time":{"start":1518044400000,"end":1518476400000},"day":{"start":160.04166666666666,"end":164.04166666666666}},{"raw":"10/2 Föreställning Finland","beskrivning":"Föreställning Finland","tag":"show","datum":"10/2","time":{"start":1518217200000,"end":1518303600000},"day":{"start":162.04166666666666,"end":162.04166666666666}},{"raw":"19/2 Seminarium","beskrivning":"Seminarium","tag":"other","datum":"19/2","time":{"start":1518994800000,"end":1519081200000},"day":{"start":171.04166666666666,"end":171.04166666666666}},{"raw":"26/3 Vårmöte","beskrivning":"Vårmöte","tag":"meeting","datum":"26/3","time":{"start":1522015200000,"end":1522101600000},"day":{"start":206,"end":206}},{"raw":"19/3   Föreställning. Omgång 2, Södra Teatern","beskrivning":"Föreställning. Omgång 2, Södra Teatern","tag":"show","datum":"19/3","time":{"start":1521414000000,"end":1521500400000},"day":{"start":199.04166666666666,"end":199.04166666666666}},{"raw":"20/3   Föreställning. Omgång 2, Södra Teatern","beskrivning":"Föreställning. Omgång 2, Södra Teatern","tag":"show","datum":"20/3","time":{"start":1521500400000,"end":1521586800000},"day":{"start":200.04166666666666,"end":200.04166666666666}},{"raw":"24/3    Bjuppfest","beskrivning":"Bjuppfest","tag":"party","datum":"24/3","time":{"start":1521846000000,"end":1521932400000},"day":{"start":204.04166666666666,"end":204.04166666666666}},{"raw":"26/3   Vårmöte","beskrivning":"Vårmöte","tag":"meeting","datum":"26/3","time":{"start":1522015200000,"end":1522101600000},"day":{"start":206,"end":206}},{"raw":"15/4    Föreställning. Omgång 3, Södra Teatern","beskrivning":"Föreställning. Omgång 3, Södra Teatern","tag":"show","datum":"15/4","time":{"start":1523743200000,"end":1523829600000},"day":{"start":226,"end":226}},{"raw":"16/4    Föreställning. Omgång 3, Södra Teatern","beskrivning":"Föreställning. Omgång 3, Södra Teatern","tag":"show","datum":"16/4","time":{"start":1523829600000,"end":1523916000000},"day":{"start":227,"end":227}},{"raw":"17/4    Föreställning. Omgång 3, Södra Teatern","beskrivning":"Föreställning. Omgång 3, Södra Teatern","tag":"show","datum":"17/4","time":{"start":1523916000000,"end":1524002400000},"day":{"start":228,"end":228}},{"raw":"21/4     Gamla Spexare-fest","beskrivning":"Gamla Spexare-fest","tag":"party","datum":"21/4","time":{"start":1524261600000,"end":1524348000000},"day":{"start":232,"end":232}},{"raw":"2/6-3/6    Mariefredsturné","beskrivning":"Mariefredsturné","tag":"tour","datum":"2/6-3/6","time":{"start":1527890400000,"end":1528063200000},"day":{"start":274,"end":275}},{"raw":"27/8    N0lle-föreställning","beskrivning":"N0lle-föreställning","tag":"show","datum":"27/8","time":{"start":1535320800000,"end":1535407200000},"day":{"start":360,"end":360}},{"raw":"28/8    Slasqueföreställning","beskrivning":"Slasqueföreställning","tag":"show","datum":"28/8","time":{"start":1535407200000,"end":1535493600000},"day":{"start":361,"end":361}},{"raw":"29/8    N0lle-föreställning","beskrivning":"N0lle-föreställning","tag":"show","datum":"29/8","time":{"start":1535493600000,"end":1535580000000},"day":{"start":362,"end":362}},{"raw":"7/9     Slutfest","beskrivning":"Slutfest","tag":"party","datum":"7/9","time":{"start":1536271200000,"end":1536357600000},"day":{"start":371,"end":371}}]},{"year":2018,"time":1535752800000,"data":[{"raw":"5/9 Kollationering","beskrivning":"Kollationering","tag":"meeting","datum":"5/9","time":{"start":1536098400000,"end":1536184800000},"day":{"start":4,"end":4}},{"raw":"14/9-16/9 Internatet, Granö gård","beskrivning":"Internatet, Granö gård","tag":"tour","datum":"14/9-16/9","time":{"start":1536876000000,"end":1537135200000},"day":{"start":13,"end":15}},{"raw":"13/10 Happening i M23/M24, M-huset","beskrivning":"Happening i M23/M24, M-huset","tag":"rehearsal","datum":"13/10","time":{"start":1539388800000,"end":1539475200000},"day":{"start":42.083333333333336,"end":42.083333333333336}},{"raw":"10/11 Checkis i Satelliten, Sollentuna","beskrivning":"Checkis i Satelliten, Sollentuna","tag":"rehearsal","datum":"10/11","time":{"start":1541808000000,"end":1541894400000},"day":{"start":70.08333333333333,"end":70.08333333333333}},{"raw":"26/11 Höstmöte, B1","beskrivning":"Höstmöte, B1","tag":"meeting","datum":"26/11","time":{"start":1543190400000,"end":1543276800000},"day":{"start":86.08333333333333,"end":86.08333333333333}},{"raw":"15/12 Smygis, Riksteatern, Hallunda","beskrivning":"Smygis, Riksteatern, Hallunda","tag":"rehearsal","datum":"15/12","time":{"start":1544832000000,"end":1544918400000},"day":{"start":105.08333333333333,"end":105.08333333333333}},{"raw":"27/1 Genrepet","beskrivning":"Genrepet","tag":"show","datum":"27/1","time":{"start":1548543600000,"end":1548630000000},"day":{"start":148.04166666666666,"end":148.04166666666666}},{"raw":"28/1 Premiär, Omgång 1, Södra teatern","beskrivning":"Premiär, Omgång 1, Södra teatern","tag":"show","datum":"28/1","time":{"start":1548630000000,"end":1548716400000},"day":{"start":149.04166666666666,"end":149.04166666666666}},{"raw":"29/1 KTH-alumni, Omgång 1, Södra teatern","beskrivning":"KTH-alumni, Omgång 1, Södra teatern","tag":"show","datum":"29/1","time":{"start":1548716400000,"end":1548802800000},"day":{"start":150.04166666666666,"end":150.04166666666666}},{"raw":"2/2 Premiärfesten","beskrivning":"Premiärfesten","tag":"party","datum":"2/2","time":{"start":1549062000000,"end":1549148400000},"day":{"start":154.04166666666666,"end":154.04166666666666}},{"raw":"21/2-25/2 Finlandsturné","beskrivning":"Finlandsturné","tag":"tour","datum":"21/2-25/2","time":{"start":1550703600000,"end":1551135600000},"day":{"start":173.04166666666666,"end":177.04166666666666}},{"raw":"23/2 Föreställning Finland","beskrivning":"Föreställning Finland","tag":"show","datum":"23/2","time":{"start":1550876400000,"end":1550962800000},"day":{"start":175.04166666666666,"end":175.04166666666666}},{"raw":"24/3 Bjuppen, Omgång 2, Södra teatern","beskrivning":"Bjuppen, Omgång 2, Södra teatern","tag":"show","datum":"24/3","time":{"start":1553382000000,"end":1553468400000},"day":{"start":204.04166666666666,"end":204.04166666666666}},{"raw":"25/3 Föreställning, Omgång 2, Södra teatern","beskrivning":"Föreställning, Omgång 2, Södra teatern","tag":"show","datum":"25/3","time":{"start":1553468400000,"end":1553554800000},"day":{"start":205.04166666666666,"end":205.04166666666666}},{"raw":"30/3 Bjupp-festen","beskrivning":"Bjupp-festen","tag":"party","datum":"30/3","time":{"start":1553900400000,"end":1553986800000},"day":{"start":210.04166666666666,"end":210.04166666666666}},{"raw":"4/4 Vårmöte","beskrivning":"Vårmöte","tag":"meeting","datum":"4/4","time":{"start":1554328800000,"end":1554415200000},"day":{"start":215,"end":215}},{"raw":"23/4 KTH-anställda, Omgång 3, Södra teatern","beskrivning":"KTH-anställda, Omgång 3, Södra teatern","tag":"show","datum":"23/4","time":{"start":1555970400000,"end":1556056800000},"day":{"start":234,"end":234}},{"raw":"24/4 Gamla spexare, Omgång 3, Södra teatern","beskrivning":"Gamla spexare, Omgång 3, Södra teatern","tag":"show","datum":"24/4","time":{"start":1556056800000,"end":1556143200000},"day":{"start":235,"end":235}},{"raw":"25/4 Föreställning, Omgång 3, Södra teatern","beskrivning":"Föreställning, Omgång 3, Södra teatern","tag":"show","datum":"25/4","time":{"start":1556143200000,"end":1556229600000},"day":{"start":236,"end":236}},{"raw":"26/4 Gamla spexare-festen","beskrivning":"Gamla spexare-festen","tag":"party","datum":"26/4","time":{"start":1556229600000,"end":1556316000000},"day":{"start":237,"end":237}},{"raw":"17/5-19/5 Turné till Örebro","beskrivning":"Turné till Örebro","tag":"tour","datum":"17/5-19/5","time":{"start":1558044000000,"end":1558303200000},"day":{"start":258,"end":260}},{"raw":"18/5 Föreställning Örebro","beskrivning":"Föreställning Örebro","tag":"show","datum":"18/5","time":{"start":1558130400000,"end":1558216800000},"day":{"start":259,"end":259}},{"raw":"10/6 Sommaravslutning","beskrivning":"Sommaravslutning","tag":"party","datum":"10/6","time":{"start":1560117600000,"end":1560204000000},"day":{"start":282,"end":282}},{"raw":"24/8 Förberedelsedag på Dieselverkstaden","beskrivning":"Förberedelsedag på Dieselverkstaden","tag":"show","datum":"24/8","time":{"start":1566597600000,"end":1566684000000},"day":{"start":357,"end":357}},{"raw":"25/8 Slasken, n0lleomgång, Dieselverkstaden","beskrivning":"Slasken, n0lleomgång, Dieselverkstaden","tag":"show","datum":"25/8","time":{"start":1566684000000,"end":1566770400000},"day":{"start":358,"end":358}},{"raw":"26/8 Föreställning, n0lleomgång, Dieselverkstaden","beskrivning":"Föreställning, n0lleomgång, Dieselverkstaden","tag":"show","datum":"26/8","time":{"start":1566770400000,"end":1566856800000},"day":{"start":359,"end":359}},{"raw":"27/8 Föreställning, n0lleomgång, Dieselverkstaden","beskrivning":"Föreställning, n0lleomgång, Dieselverkstaden","tag":"show","datum":"27/8","time":{"start":1566856800000,"end":1566943200000},"day":{"start":360,"end":360}},{"raw":"31/8 Slutfesten, Stora gasque i Nymble","beskrivning":"Slutfesten, Stora gasque i Nymble","tag":"party","datum":"31/8","time":{"start":1567202400000,"end":1567288800000},"day":{"start":364,"end":364}}]},{"year":2019,"time":1567288800000,"data":[{"raw":"13-15/9 Internat","beskrivning":"Internat","tag":"tour","datum":"15/9","time":{"start":1568498400000,"end":1568584800000},"day":{"start":14,"end":14}},{"raw":"23/11 Checkis","beskrivning":"Checkis","tag":"rehearsal","datum":"23/11","time":{"start":1574467200000,"end":1574553600000},"day":{"start":83.08333333333333,"end":83.08333333333333}},{"raw":"6/12-8/12 Fondmålning","beskrivning":"Fondmålning","tag":"other","datum":"6/12-8/12","time":{"start":1575586800000,"end":1575846000000},"day":{"start":96.04166666666667,"end":98.04166666666667}},{"raw":"8/12 Musikgenomdrag","beskrivning":"Musikgenomdrag","tag":"rehearsal","datum":"8/12","time":{"start":1607382000000,"end":1607468400000},"day":{"start":464.0416666666667,"end":464.0416666666667}},{"raw":"4/1 Tekniskt genomdrag","beskrivning":"Tekniskt genomdrag","tag":"rehearsal","datum":"4/1","time":{"start":1578092400000,"end":1578178800000},"day":{"start":125.04166666666667,"end":125.04166666666667}},{"raw":"5/1 Smygis","beskrivning":"Smygis","tag":"rehearsal","datum":"5/1","time":{"start":1578178800000,"end":1578265200000},"day":{"start":126.04166666666667,"end":126.04166666666667}},{"raw":"19/1 Genrep","beskrivning":"Genrep","tag":"show","datum":"19/1","time":{"start":1579388400000,"end":1579474800000},"day":{"start":140.04166666666666,"end":140.04166666666666}},{"raw":"20/1 Premiär","beskrivning":"Premiär","tag":"show","datum":"20/1","time":{"start":1579474800000,"end":1579561200000},"day":{"start":141.04166666666666,"end":141.04166666666666}},{"raw":"21/1 Föreställning","beskrivning":"Föreställning","tag":"show","datum":"21/1","time":{"start":1579561200000,"end":1579647600000},"day":{"start":142.04166666666666,"end":142.04166666666666}},{"raw":"22/1 Föreställning","beskrivning":"Föreställning","tag":"show","datum":"22/1","time":{"start":1579647600000,"end":1579734000000},"day":{"start":143.04166666666666,"end":143.04166666666666}},{"raw":"25/1 Premiärfest","beskrivning":"Premiärfest","tag":"party","datum":"25/1","time":{"start":1579906800000,"end":1579993200000},"day":{"start":146.04166666666666,"end":146.04166666666666}},{"raw":"20/2-24/2 Finland","beskrivning":"Finland","tag":"tour","datum":"20/2-24/2","time":{"start":1582153200000,"end":1582585200000},"day":{"start":172.04166666666666,"end":176.04166666666666}},{"raw":"22/2 Föreställning Finland","beskrivning":"Föreställning Finland","tag":"show","datum":"22/2","time":{"start":1582326000000,"end":1582412400000},"day":{"start":174.04166666666666,"end":174.04166666666666}},{"raw":"23/8 Filmad föreställning","beskrivning":"Filmad föreställning","tag":"show","datum":"23/8","time":{"start":1598133600000,"end":1598220000000},"day":{"start":357,"end":357}}]},{"year":2020,"time":1598911200000,"data":[{"raw":"3/10 Happening","beskrivning":"Happening","tag":"rehearsal","datum":"3/10","time":{"start":1601676000000,"end":1601762400000},"day":{"start":32,"end":32}},{"raw":"3/12 Höstmöte","beskrivning":"Höstmöte","tag":"meeting","datum":"3/12","time":{"start":1606950000000,"end":1607036400000},"day":{"start":93.04166666666667,"end":93.04166666666667}}]}]